Blahhhhh/DL4Test.py
Blahhhhh/__init__.py
blahhhhh-0.0.1.dist-info/METADATA
blahhhhh-0.0.1.dist-info/WHEEL
blahhhhh-0.0.1.dist-info/licenses/LICENSE
blahhhhh-0.0.1.dist-info/RECORD
