Metadata-Version: 2.1
Name: Blahhhhh
Version: 0.0.1
Summary: The package used to defeat the evil dragon many years ago, Smells like a relic!
Author-email: Lord Yanny Von Funny The 3rd <skipper.cmd@gmail.com>
License-File: LICENSE
Classifier: License :: OSI Approved :: MIT License
Classifier: Operating System :: OS Independent
Classifier: Programming Language :: Python
Requires-Python: >=3.8
